galcv/__init__.py
galcv/sigma0fM_interp.npy
galcv/varepsilonCV_PSfrac_z10_zW0.10.pkl
galcv/varepsilonCV_PSfrac_z10_zW0.15.pkl
galcv/varepsilonCV_PSfrac_z10_zW0.25.pkl
galcv/varepsilonCV_PSfrac_z10_zW0.50.pkl
galcv/varepsilonCV_PSfrac_z10_zW0.75.pkl
galcv/varepsilonCV_PSfrac_z10_zW1.00.pkl
galcv/varepsilonCV_PSfrac_z10_zW1.50.pkl
galcv/varepsilonCV_PSfrac_z10_zW2.00.pkl
galcv/varepsilonCV_PSfrac_z11_zW0.10.pkl
galcv/varepsilonCV_PSfrac_z11_zW0.15.pkl
galcv/varepsilonCV_PSfrac_z11_zW0.25.pkl
galcv/varepsilonCV_PSfrac_z11_zW0.50.pkl
galcv/varepsilonCV_PSfrac_z11_zW0.75.pkl
galcv/varepsilonCV_PSfrac_z11_zW1.00.pkl
galcv/varepsilonCV_PSfrac_z11_zW1.50.pkl
galcv/varepsilonCV_PSfrac_z11_zW2.00.pkl
galcv/varepsilonCV_PSfrac_z12_zW0.10.pkl
galcv/varepsilonCV_PSfrac_z12_zW0.15.pkl
galcv/varepsilonCV_PSfrac_z12_zW0.25.pkl
galcv/varepsilonCV_PSfrac_z12_zW0.50.pkl
galcv/varepsilonCV_PSfrac_z12_zW0.75.pkl
galcv/varepsilonCV_PSfrac_z12_zW1.00.pkl
galcv/varepsilonCV_PSfrac_z12_zW1.50.pkl
galcv/varepsilonCV_PSfrac_z12_zW2.00.pkl
galcv/varepsilonCV_PSfrac_z13_zW0.10.pkl
galcv/varepsilonCV_PSfrac_z13_zW0.15.pkl
galcv/varepsilonCV_PSfrac_z13_zW0.25.pkl
galcv/varepsilonCV_PSfrac_z13_zW0.50.pkl
galcv/varepsilonCV_PSfrac_z13_zW0.75.pkl
galcv/varepsilonCV_PSfrac_z13_zW1.00.pkl
galcv/varepsilonCV_PSfrac_z13_zW1.50.pkl
galcv/varepsilonCV_PSfrac_z13_zW2.00.pkl
galcv/varepsilonCV_PSfrac_z14_zW0.10.pkl
galcv/varepsilonCV_PSfrac_z14_zW0.15.pkl
galcv/varepsilonCV_PSfrac_z14_zW0.25.pkl
galcv/varepsilonCV_PSfrac_z14_zW0.50.pkl
galcv/varepsilonCV_PSfrac_z14_zW0.75.pkl
galcv/varepsilonCV_PSfrac_z14_zW1.00.pkl
galcv/varepsilonCV_PSfrac_z14_zW1.50.pkl
galcv/varepsilonCV_PSfrac_z14_zW2.00.pkl
galcv/varepsilonCV_PSfrac_z15_zW0.10.pkl
galcv/varepsilonCV_PSfrac_z15_zW0.15.pkl
galcv/varepsilonCV_PSfrac_z15_zW0.25.pkl
galcv/varepsilonCV_PSfrac_z15_zW0.50.pkl
galcv/varepsilonCV_PSfrac_z15_zW0.75.pkl
galcv/varepsilonCV_PSfrac_z15_zW1.00.pkl
galcv/varepsilonCV_PSfrac_z15_zW1.50.pkl
galcv-1.1.1.dist-info/LICENSE
galcv-1.1.1.dist-info/METADATA
galcv-1.1.1.dist-info/WHEEL
galcv-1.1.1.dist-info/top_level.txt
galcv-1.1.1.dist-info/RECORD
