Metadata-Version: 2.1
Name: galcv
Version: 1.1.1
Summary: A simple calculator for cosmic variance
Home-page: https://github.com/adamtrapp/galcv
Author: Adam Trapp
Author-email: atrapp@astro.ucla.edu
License: MIT
Keywords: Cosmology Cosmic Variance Galaxies
Platform: UNKNOWN
Classifier: Development Status :: 5 - Production/Stable
Classifier: License :: OSI Approved :: MIT License
Classifier: Programming Language :: Python :: 3.7
Classifier: Topic :: Scientific/Engineering
Requires-Python: ~=3.3
Requires-Dist: numpy
Requires-Dist: pandas
Requires-Dist: scipy
